__init__.py
micro_logging.py
micro_logging-0.0.33.dist-info/METADATA
micro_logging-0.0.33.dist-info/WHEEL
micro_logging-0.0.33.dist-info/top_level.txt
micro_logging-0.0.33.dist-info/RECORD
