Metadata-Version: 2.1
Name: micro-logging
Version: 0.0.33
Summary: A logging solution to connect all your microservices :) 
Author-email: Max Paul <maxkpaul21@gmail.com>
Classifier: Programming Language :: Python :: 3
Classifier: License :: OSI Approved :: MIT License
Classifier: Operating System :: OS Independent
Requires-Python: >=3.7
